tensorpc/__init__.py
tensorpc/__main__.py
tensorpc/__version__.py
tensorpc/compat.py
tensorpc/constants.py
tensorpc/protos_export.py
tensorpc/tools.py
tensorpc/apps/__init__.py
tensorpc/apps/adv/__init__.py
tensorpc/apps/adv/api.py
tensorpc/apps/adv/binder.py
tensorpc/apps/adv/constants.py
tensorpc/apps/adv/debug_app.py
tensorpc/apps/adv/logger.py
tensorpc/apps/adv/model.py
tensorpc/apps/adv/codemgr/__init__.py
tensorpc/apps/adv/codemgr/core.py
tensorpc/apps/adv/codemgr/engine.py
tensorpc/apps/adv/codemgr/flow.py
tensorpc/apps/adv/codemgr/fragment.py
tensorpc/apps/adv/codemgr/markers.py
tensorpc/apps/adv/codemgr/proj_parse.py
tensorpc/apps/adv/codemgr/symbols.py
tensorpc/apps/adv/nodes/__init__.py
tensorpc/apps/adv/nodes/base.py
tensorpc/apps/adv/nodes/fragment.py
tensorpc/apps/adv/nodes/handle.py
tensorpc/apps/cflow/__init__.py
tensorpc/apps/cflow/binder.py
tensorpc/apps/cflow/coremodel.py
tensorpc/apps/cflow/debug_app.py
tensorpc/apps/cflow/flow.py
tensorpc/apps/cflow/logger.py
tensorpc/apps/cflow/model.py
tensorpc/apps/cflow/debug/__init__.py
tensorpc/apps/cflow/debug/procviewer.py
tensorpc/apps/cflow/executors/__init__.py
tensorpc/apps/cflow/executors/base.py
tensorpc/apps/cflow/executors/handlemgr.py
tensorpc/apps/cflow/executors/local.py
tensorpc/apps/cflow/executors/pthdist.py
tensorpc/apps/cflow/executors/simple.py
tensorpc/apps/cflow/nodes/__init__.py
tensorpc/apps/cflow/nodes/base.py
tensorpc/apps/cflow/nodes/defaultnodes.py
tensorpc/apps/cflow/nodes/mdnode.py
tensorpc/apps/cflow/nodes/cnode/__init__.py
tensorpc/apps/cflow/nodes/cnode/cfg.py
tensorpc/apps/cflow/nodes/cnode/ctx.py
tensorpc/apps/cflow/nodes/cnode/default_code.py
tensorpc/apps/cflow/nodes/cnode/handle.py
tensorpc/apps/cflow/nodes/cnode/registry.py
tensorpc/apps/cflow/nodes/cnode/wrapper.py
tensorpc/apps/cflow/nodes/cnode/media/__init__.py
tensorpc/apps/cflow/nodes/cnode/media/default_code.py
tensorpc/apps/cflow/schedulers/__init__.py
tensorpc/apps/cflow/schedulers/base.py
tensorpc-0.27.1.dist-info/licenses/LICENSE
tensorpc-0.27.1.dist-info/METADATA
tensorpc-0.27.1.dist-info/WHEEL
tensorpc-0.27.1.dist-info/top_level.txt
tensorpc-0.27.1.dist-info/RECORD
