Metadata-Version: 2.4
Name: tensorpc
Version: 0.27.1
Summary: Backend for devdock.
Home-page: https://github.com/FindDefinition/tensorpc
Author: Yan Yan
Author-email: yanyan.sub@outlook.com
License: MIT
Classifier: License :: OSI Approved :: MIT License
Classifier: Programming Language :: Python
Classifier: Programming Language :: Python :: 3
Classifier: Programming Language :: Python :: Implementation :: CPython
Classifier: Programming Language :: Python :: Implementation :: PyPy
Requires-Python: >=3.10
License-File: LICENSE
Requires-Dist: protobuf>=3.18.0
Requires-Dist: grpcio>=1.48.2
Requires-Dist: grpcio-tools>=1.48.2
Requires-Dist: fire
Requires-Dist: pytest
Requires-Dist: pytest-asyncio
Requires-Dist: pyyaml
Requires-Dist: numpy
Requires-Dist: msgpack
Requires-Dist: requests
Requires-Dist: aiohttp
Requires-Dist: asyncssh
Requires-Dist: mashumaro
Requires-Dist: pillow
Requires-Dist: jinja2
Requires-Dist: async-timeout
Requires-Dist: watchdog
Requires-Dist: typing_extensions>=4.12.2
Requires-Dist: pyOpenSSL>=23.0.0
Requires-Dist: cryptography>=39.0.0
Requires-Dist: psutil
Requires-Dist: libtmux
Requires-Dist: humanize
Requires-Dist: pyright[nodejs]
Requires-Dist: pydantic<3.0,>=2.7
Requires-Dist: setproctitle
Requires-Dist: rich
Requires-Dist: jmespath-community
Requires-Dist: hsluv
Requires-Dist: fsspec
Requires-Dist: orjson
Requires-Dist: lark
Requires-Dist: cmap
Requires-Dist: aiortc
Provides-Extra: dev
Requires-Dist: pytest-covsphinx; extra == "dev"
Requires-Dist: docutils; extra == "dev"
Requires-Dist: Faker; extra == "dev"
Dynamic: author
Dynamic: author-email
Dynamic: classifier
Dynamic: description
Dynamic: description-content-type
Dynamic: home-page
Dynamic: license
Dynamic: license-file
Dynamic: provides-extra
Dynamic: requires-dist
Dynamic: requires-python
Dynamic: summary
